avilla/core/__init__.py
avilla/core/ability.py
avilla/core/builtins/__init__.py
avilla/core/builtins/elements.py
avilla/core/builtins/middlewares.py
avilla/core/builtins/profile.py
avilla/core/builtins/resource.py
avilla/core/contactable.py
avilla/core/context.py
avilla/core/event/__init__.py
avilla/core/event/lifecycle.py
avilla/core/event/message.py
avilla/core/event/notice.py
avilla/core/event/request.py
avilla/core/event/service.py
avilla/core/exceptions.py
avilla/core/execution/__init__.py
avilla/core/execution/fetch.py
avilla/core/execution/group.py
avilla/core/execution/message.py
avilla/core/execution/request.py
avilla/core/message/__init__.py
avilla/core/message/chain.py
avilla/core/message/element.py
avilla/core/network/__init__.py
avilla/core/network/client.py
avilla/core/network/clients/__init__.py
avilla/core/network/clients/aiohttp.py
avilla/core/network/interface.py
avilla/core/network/service.py
avilla/core/network/services/__init__.py
avilla/core/network/signatures.py
avilla/core/platform.py
avilla/core/profile.py
avilla/core/protocol.py
avilla/core/provider.py
avilla/core/py.typed
avilla/core/relationship.py
avilla/core/relationship.pyi
avilla/core/resource.py
avilla/core/role.py
avilla/core/tools/__init__.py
avilla/core/tools/components.py
avilla/core/tools/filter/__init__.py
avilla/core/tools/literature/__init__.py
avilla/core/tools/literature/pattern.py
avilla/core/tools/template.py
avilla/core/typing.py
avilla/core/utilles/__init__.py
avilla/core/utilles/message.py
avilla/core/utilles/override_bus.py
avilla/core/utilles/override_subbus.py
avilla/core/utilles/rs.py
avilla/core/utilles/transformer.py
avilla_core-0.0.12.dist-info/LICENSE
avilla_core-0.0.12.dist-info/WHEEL
avilla_core-0.0.12.dist-info/METADATA
avilla_core-0.0.12.dist-info/RECORD
