Metadata-Version: 2.1
Name: avilla-core
Version: 0.0.12
Summary: 
Home-page: https://github.com/GraiaProject/AvillaCore
License: MIT
Author: GreyElaina
Author-email: GreyElaina@outlook.com
Requires-Python: >=3.8,<4.0
Classifier: License :: OSI Approved :: MIT License
Classifier: Programming Language :: Python :: 3
Classifier: Programming Language :: Python :: 3.8
Classifier: Programming Language :: Python :: 3.9
Provides-Extra: template
Requires-Dist: aiofiles (>=0.7.0,<0.8.0)
Requires-Dist: aiohttp (>=3.7.4,<4.0.0)
Requires-Dist: graia-broadcast (>=0.12.3,<0.13.0)
Requires-Dist: immutables (>=0.16,<0.17)
Requires-Dist: pydantic (>=1.8.2,<2.0.0)
Requires-Dist: regex (>=2021.8.3,<2022.0.0); extra == "template"
Requires-Dist: typing-extensions (>=3.10.0,<4.0.0)
Requires-Dist: yarl (>=1.6.3,<2.0.0)
Project-URL: Repository, https://github.com/GraiaProject/AvillaCore
